rri.py
pyrri-0.2.1.dist-info/METADATA
pyrri-0.2.1.dist-info/WHEEL
pyrri-0.2.1.dist-info/entry_points.txt
pyrri-0.2.1.dist-info/licenses/LICENSE.TXT
pyrri-0.2.1.dist-info/RECORD
