Metadata-Version: 2.4
Name: pyrri
Version: 0.2.1
Summary: Send and receive DENIC RRI commands
Project-URL: Repository, https://github.com/clerie/pyrri
Maintainer-email: clerie <hallo@clerie.de>
License: Copyright (c) 2019 DENIC eG
License-File: LICENSE.TXT
Requires-Python: >=3.9
